cryptodataaccess/Memory.py
cryptodataaccess/RatesRepository.py
cryptodataaccess/Repository.py
cryptodataaccess/TransactionRepository.py
cryptodataaccess/UsersRepository.py
cryptodataaccess/__init__.py
cryptodataaccess/config.py
cryptodataaccess/helpers.py
cryptodataaccess/Calculator/CalculatorMongoStore.py
cryptodataaccess/Calculator/CalculatorRepository.py
cryptodataaccess/Calculator/CalculatorStore.py
cryptodataaccess/Calculator/__init__.py
cryptodataaccess/Notifications/NotificationsMongoStore.py
cryptodataaccess/Notifications/NotificationsRepository.py
cryptodataaccess/Notifications/NotificationsStore.py
cryptodataaccess/Notifications/__init__.py
cryptodataaccess/Rates/RatesMongoStore.py
cryptodataaccess/Rates/RatesRepository.py
cryptodataaccess/Rates/RatesStore.py
cryptodataaccess/Rates/__init__.py
cryptodataaccess/Transactions/TransactionMongoStore.py
cryptodataaccess/Transactions/TransactionRepository.py
cryptodataaccess/Transactions/TransactionStore.py
cryptodataaccess/Transactions/__init__.py
cryptodataaccess/Users/UsersMongoStore.py
cryptodataaccess/Users/UsersRepository.py
cryptodataaccess/Users/UsersStore.py
cryptodataaccess/Users/__init__.py
cryptodataaccess/tests/CalculatorRepository_test.py
cryptodataaccess/tests/Notifications_Repository_test.py
cryptodataaccess/tests/RatesMongoStore_test.py
cryptodataaccess/tests/TransactionRepository_test.py
cryptodataaccess/tests/UsersRepository_test.py
cryptodataaccess/tests/__init__.py
cryptodataaccess/tests/helpers.py
dataaccess/Repository.py
dataaccess/TransactionRepository.py
dataaccess/__init__.py
dataaccess/config.py
dataaccess/helpers.py
tests/CalculatorRepository_test.py
tests/RatesMongoStore_test.py
tests/Repository_test.py
tests/TransactionRepository_test.py
tests/UsersRepository_test.py
tests/__init__.py
tests/helpers.py
cryptodataaccess_athanikos-0.6.6.dist-info/LICENSE
cryptodataaccess_athanikos-0.6.6.dist-info/METADATA
cryptodataaccess_athanikos-0.6.6.dist-info/WHEEL
cryptodataaccess_athanikos-0.6.6.dist-info/top_level.txt
cryptodataaccess_athanikos-0.6.6.dist-info/RECORD
