Metadata-Version: 2.1
Name: cryptodataaccess-athanikos
Version: 0.6.6
Summary: data access layer for crypto model  
Home-page: UNKNOWN
Author: Nikos Athanasakis
Author-email: athanikos@gmail.com
License: MIT License
Platform: UNKNOWN
Classifier: Development Status :: 1 - Planning
Classifier: License :: OSI Approved :: MIT License
Classifier: Operating System :: OS Independent
